tffm/__init__.py
tffm/base.py
tffm/core.py
tffm/models.py
tffm/utils.py
tffm-1.0.2.dist-info/LICENSE
tffm-1.0.2.dist-info/METADATA
tffm-1.0.2.dist-info/WHEEL
tffm-1.0.2.dist-info/top_level.txt
tffm-1.0.2.dist-info/RECORD
