Metadata-Version: 2.1
Name: tffm
Version: 1.0.2
Summary: TensforFlow implementation of arbitrary order Factorization Machine
Home-page: https://github.com/geffy/tffm
Author: Mikhail Trofimov
Author-email: mikhail.trofimov@phystech.edu
License: MIT
Download-URL: https://github.com/geffy/tffm/archive/1.0.2.tar.gz
Platform: UNKNOWN
Classifier: Development Status :: 3 - Alpha
Classifier: Intended Audience :: Science/Research
Classifier: Topic :: Scientific/Engineering
Classifier: License :: OSI Approved :: MIT License
Classifier: Programming Language :: Python :: 2.7
Classifier: Programming Language :: Python :: 3
License-File: LICENSE
Requires-Dist: scikit-learn
Requires-Dist: numpy
Requires-Dist: tqdm
